LICENSE
MANIFEST.in
README.rst
setup.cfg
setup.py
PyHive_dm.egg-info/PKG-INFO
PyHive_dm.egg-info/SOURCES.txt
PyHive_dm.egg-info/dependency_links.txt
PyHive_dm.egg-info/entry_points.txt
PyHive_dm.egg-info/requires.txt
PyHive_dm.egg-info/top_level.txt
TCLIService/TCLIService.py
TCLIService/__init__.py
TCLIService/constants.py
TCLIService/ttypes.py
pyhive/__init__.py
pyhive/common.py
pyhive/exc.py
pyhive/hive.py
pyhive/presto.py
pyhive/sqlalchemy_hive.py
pyhive/sqlalchemy_presto.py