Metadata-Version: 2.1
Name: PyHive-dm
Version: 0.6.2
Summary: Python interface to Hive
Home-page: https://github.com/dropbox/PyHive
Author: ppikaqiu
Author-email: 1207648300@qq.com
License: Apache License, Version 2.0
Platform: UNKNOWN
Classifier: Intended Audience :: Developers
Classifier: License :: OSI Approved :: Apache Software License
Classifier: Operating System :: OS Independent
Classifier: Topic :: Database :: Front-Ends
Provides-Extra: presto
Provides-Extra: hive
Provides-Extra: sqlalchemy
License-File: LICENSE
